chain/__init__.py
chain/core/__init__.py
chain/core/domains/__init__.py
chain/core/domains/chain/__init__.py
chain/core/domains/chain/chain.py
chain/core/domains/chain/decorator.py
chain/core/domains/context/__init__.py
chain/core/domains/context/context.py
chain/core/domains/state/__init__.py
chain/core/domains/state/state.py
python_chain-1.0.4.data/scripts/build_chain.py
python_chain-1.0.4.dist-info/LICENSE
python_chain-1.0.4.dist-info/METADATA
python_chain-1.0.4.dist-info/WHEEL
python_chain-1.0.4.dist-info/top_level.txt
python_chain-1.0.4.dist-info/RECORD
