Metadata-Version: 2.1
Name: python-chain
Version: 1.0.4
Summary: An easy to use pattern of function chaining on Python.
Home-page: https://github.com/quintoandar/python-chain/
Author: QuintoAndar
Author-email: daniel.fonseca@quintoandar.com.br
License: UNKNOWN
Platform: UNKNOWN
Classifier: Programming Language :: Python :: 3
Classifier: License :: OSI Approved :: MIT License
Classifier: Operating System :: OS Independent
Requires-Dist: injectable (==3.0.1)
